{
    "skos:prefLabel": "1940.499957",
    "rdf:type": "1940.499957",
    "rdfs:label": "1940.499957",
    "owl:sameAs": "646.499871",
    "yr:hasFamilyName": "1.875987",
    "yr:hasGivenName": "1.875987",
    "yr:hasGender": "1.875987",
    "yr:wasBornOnDate": "1.875987",
    "yr:redirectedFrom": "1940.499957",
    "yr:wasBornIn": "1.875987",
    "yr:isAffiliatedTo": "1.684417",
    "yr:playsFor": "1.697724",
    "yr:hasHeight": "1.183817",
    "yr:created": "1.836440",
    "yr:hasWebsite": "1.610041",
    "yr:hasWonPrize": "2.086740",
    "yr:graduatedFrom": "1.209337",
    "yr:actedIn": "0.977766",
    "yr:isCitizenOf": "1.314378",
    "yr:livesIn": "1.154009",
    "yr:hasWeight": "0.861487",
    "yr:isMarriedTo": "1.660831",
    "yr:hasMusicalRole": "0.768130",
    "yr:isPoliticianOf": "0.919243",
    "yr:wasCreatedOnDate": "107.332557",
    "yr:directed": "1.054605",
    "yr:isLeaderOf": "1.355148",
    "yr:hasChild": "1.212788",
    "yr:diedOnDate": "1.875987",
    "yr:wroteMusicFor": "1.057567",
    "yr:worksAt": "0.688297",
    "yr:hasAcademicAdvisor": "0.735100",
    "yr:influences": "0.998525",
    "yr:owns": "1.028331",
    "yr:hasMotto": "0.657365",
    "yr:wasDestroyedOnDate": "2.608913",
    "yr:edited": "0.460237",
    "yr:isInterestedIn": "0.515531",
    "yr:diedIn": "1.851505",
    "yr:isKnownFor": "0.503154",
    "yr:hasLatitude": "0.887447",
    "yr:hasLongitude": "0.887447",
    "yr:hasPages": "0.408665",
    "yr:hasNumberOfPeople": "0.466938",
    "yr:hasRevenue": "0.265654",
    "yr:participatedIn": "0.406674",
    "yr:hasDuration": "0.418555",
    "yr:isLocatedIn": "0.790712",
    "yr:hasArea": "0.390576",
    "yr:hasPopulationDensity": "0.331446",
    "yr:hasCapital": "0.231865",
    "yr:hasOfficialLanguage": "0.216145",
    "yr:hasCurrency": "0.216145",
    "yr:isConnectedTo": "0.202762",
    "yr:hasTLD": "0.202762",
    "yr:hasAirportCode": "0.202762",
    "yr:hasUnemployment": "0.202762",
    "yr:dealsWith": "0.202762",
    "yr:hasPoverty": "0.177776",
    "yr:hasGDP": "0.196616",
    "yr:exports": "0.189812",
    "yr:hasExport": "0.196616",
    "yr:hasImport": "0.196616",
    "yr:hasEconomicGrowth": "0.196616",
    "yr:imports": "0.196616",
    "yr:hasLength": "0.268759",
    "yr:hasGini": "0.182099",
    "yr:hasInflation": "0.189812",
    "yr:hasExpenses": "0.199760",
    "yr:hasBudget": "0.216145",
    "yr:happenedOnDate": "0.504106",
    "yr:hasImdb": "0.273304",
    "yr:hasNeighbor": "0.177776",
    "yr:happenedIn": "0.293077",
    "yr:hasISBN": "0.225456",
    "yr:isPreferredMeaningOf": "0.161690",
    "yr:startedOnDate": "0.145395",
    "yr:hasLanguageCode": "0.167742",
    "yr:hasThreeLetterLanguageCode": "0.177776"
}